odoo/addons/kpi_dashboard_altair/README.rst
odoo/addons/kpi_dashboard_altair/__init__.py
odoo/addons/kpi_dashboard_altair/__manifest__.py
odoo/addons/kpi_dashboard_altair/demo/demo_dashboard_altair.xml
odoo/addons/kpi_dashboard_altair/i18n/kpi_dashboard_altair.pot
odoo/addons/kpi_dashboard_altair/models/__init__.py
odoo/addons/kpi_dashboard_altair/models/kpi_kpi.py
odoo/addons/kpi_dashboard_altair/readme/CONFIGURE.rst
odoo/addons/kpi_dashboard_altair/readme/CONTRIBUTORS.rst
odoo/addons/kpi_dashboard_altair/readme/DESCRIPTION.rst
odoo/addons/kpi_dashboard_altair/readme/USAGE.rst
odoo/addons/kpi_dashboard_altair/static/description/config.png
odoo/addons/kpi_dashboard_altair/static/description/graph.png
odoo/addons/kpi_dashboard_altair/static/description/icon.png
odoo/addons/kpi_dashboard_altair/static/description/index.html
odoo/addons/kpi_dashboard_altair/static/lib/vega/vega-embed.min.js
odoo/addons/kpi_dashboard_altair/static/lib/vega/vega-lite.min.js
odoo/addons/kpi_dashboard_altair/static/lib/vega/vega.min.js
odoo/addons/kpi_dashboard_altair/static/src/js/altair_widget.js
odoo/addons/kpi_dashboard_altair/static/src/xml/dashboard.xml
odoo/addons/kpi_dashboard_altair/views/webclient_templates.xml
odoo12_addon_kpi_dashboard_altair-12.0.1.0.3.dist-info/METADATA
odoo12_addon_kpi_dashboard_altair-12.0.1.0.3.dist-info/WHEEL
odoo12_addon_kpi_dashboard_altair-12.0.1.0.3.dist-info/top_level.txt
odoo12_addon_kpi_dashboard_altair-12.0.1.0.3.dist-info/RECORD
