Metadata-Version: 2.1
Name: odoo12-addon-kpi-dashboard-altair
Version: 12.0.1.0.3
Summary: Create dashboards using altair
Home-page: https://github.com/OCA/reporting-engine
Author: Creu Blanca,Odoo Community Association (OCA)
Author-email: support@odoo-community.org
License: AGPL-3
Platform: UNKNOWN
Classifier: Programming Language :: Python
Classifier: Framework :: Odoo
Classifier: License :: OSI Approved :: GNU Affero General Public License v3
Requires-Python: >=3.5
Requires-Dist: altair
Requires-Dist: odoo12-addon-kpi-dashboard
Requires-Dist: odoo (<12.1dev,>=12.0a)
